.coveragerc
.editorconfig
.gitignore
.travis.yml
LICENSE
README.md
pyproject.toml
requirements.txt
requirements_dev.txt
setup.cfg
setup.py
.github/workflows/python-publish.yml
democritus_converters/__init__.py
democritus_converters/converter.py
democritus_converters/converter_temp_utils.py
democritus_converters/distance_converter.py
democritus_converters/temperature_converter.py
democritus_converters/time_converter.py
democritus_converters.egg-info/PKG-INFO
democritus_converters.egg-info/SOURCES.txt
democritus_converters.egg-info/dependency_links.txt
democritus_converters.egg-info/requires.txt
democritus_converters.egg-info/top_level.txt
democritus_converters.egg-info/zip-safe
tests/__init__.py
tests/test_converter.py
tests/test_distance_converter.py
tests/test_temperature_converter.py
tests/test_time_converter.py